<?xml version="1.0" encoding="utf-8"?>
<openerp>
    <data noupdate="0">
        
        <!-- Catálogo No. 01 - Código de Tipo de documento -->
        <record id="e01_00" model="einvoice.catalog.01"><field name="code">00</field><field name="name">Otros</field></record>
        <record id="e01_01" model="einvoice.catalog.01"><field name="code">01</field><field name="name">Factura</field></record>
        <record id="e01_02" model="einvoice.catalog.01"><field name="code">02</field><field name="name">Recibo por Honorarios</field></record>
        <record id="e01_03" model="einvoice.catalog.01"><field name="code">03</field><field name="name">Boleta de Venta</field></record>
        <record id="e01_04" model="einvoice.catalog.01"><field name="code">04</field><field name="name">Liquidación de compra</field></record>
        <record id="e01_05" model="einvoice.catalog.01"><field name="code">05</field><field name="name">Boleto de compañía de aviación comercial por el servicio de transporte aéreo de pasajeros</field></record>
        <record id="e01_06" model="einvoice.catalog.01"><field name="code">06</field><field name="name">Carta de porte aéreo por el servicio de transporte de carga aérea</field></record>
        <record id="e01_07" model="einvoice.catalog.01"><field name="code">07</field><field name="name">Nota de crédito</field></record>
        <record id="e01_08" model="einvoice.catalog.01"><field name="code">08</field><field name="name">Nota de débito</field></record>
        <record id="e01_09" model="einvoice.catalog.01"><field name="code">09</field><field name="name">Guía de remisión - Remitente</field></record>
        <record id="e01_10" model="einvoice.catalog.01"><field name="code">10</field><field name="name">Recibo por Arrendamiento</field></record>
        <record id="e01_11" model="einvoice.catalog.01"><field name="code">11</field><field name="name">Póliza emitida por las Bolsas de Valores, Bolsas de Productos o Agentes de Intermediación por operaciones realizadas en las Bolsas de Valores o Productos o fuera de las mismas, autorizadas por CONASEV</field></record>
        <record id="e01_12" model="einvoice.catalog.01"><field name="code">12</field><field name="name">Ticket o cinta emitido por máquina registradora</field></record>
        <record id="e01_13" model="einvoice.catalog.01"><field name="code">13</field><field name="name">Documento emitido por bancos, instituciones financieras, crediticias y de seguros que se encuentren bajo el control de la Superintendencia de Banca y Seguros</field></record>
        <record id="e01_14" model="einvoice.catalog.01"><field name="code">14</field><field name="name">Recibo por servicios públicos de suministro de energía eléctrica, agua, teléfono, telex y telegráficos y otros servicios complementarios que se incluyan en el recibo de servicio público</field></record>
        <record id="e01_15" model="einvoice.catalog.01"><field name="code">15</field><field name="name">Boleto emitido por las empresas de transporte público urbano de pasajeros</field></record>
        <record id="e01_16" model="einvoice.catalog.01"><field name="code">16</field><field name="name">Boleto de viaje emitido por las empresas de transporte público interprovincial de pasajeros dentro del país</field></record>
        <record id="e01_17" model="einvoice.catalog.01"><field name="code">17</field><field name="name">Documento emitido por la Iglesia Católica por el arrendamiento de bienes inmuebles</field></record>
        <record id="e01_18" model="einvoice.catalog.01"><field name="code">18</field><field name="name">Documento emitido por las Administradoras Privadas de Fondo de Pensiones que se encuentran bajo la supervisión de la Superintendencia de Administradoras Privadas de Fondos de Pensiones</field></record>
        <record id="e01_19" model="einvoice.catalog.01"><field name="code">19</field><field name="name">Boleto o entrada por atracciones y espectáculos públicos</field></record>
        <record id="e01_20" model="einvoice.catalog.01"><field name="code">20</field><field name="name">Comprobante de Retención</field></record>
        <record id="e01_21" model="einvoice.catalog.01"><field name="code">21</field><field name="name">Conocimiento de embarque por el servicio de transporte de carga marítima</field></record>
        <record id="e01_22" model="einvoice.catalog.01"><field name="code">22</field><field name="name">Comprobante por Operaciones No Habituales</field></record>
        <record id="e01_23" model="einvoice.catalog.01"><field name="code">23</field><field name="name">Pólizas de Adjudicación emitidas con ocasión del remate o adjudicación de bienes por venta forzada, por los martilleros o las entidades que rematen o subasten bienes por cuenta de terceros</field></record>
        <record id="e01_24" model="einvoice.catalog.01"><field name="code">24</field><field name="name">Certificado de pago de regalías emitidas por PERUPETRO S.A</field></record>
        <record id="e01_25" model="einvoice.catalog.01"><field name="code">25</field><field name="name">Documento de Atribución (Ley del Impuesto General a las Ventas e Impuesto Selectivo al Consumo, Art. 19º, último párrafo, R.S. N° 022-98-SUNAT).</field></record>
        <record id="e01_26" model="einvoice.catalog.01"><field name="code">26</field><field name="name">Recibo por el Pago de la Tarifa por Uso de Agua Superficial con fines agrarios y por el pago de la Cuota para la ejecución de una determinada obra o actividad acordada por la Asamblea General de la Comisión de Regantes o Resolución expedida por el Jefe de la Unidad de Aguas y de Riego (Decreto Supremo N° 003-90-AG, Arts. 28 y 48)</field></record>
        <record id="e01_27" model="einvoice.catalog.01"><field name="code">27</field><field name="name">Seguro Complementario de Trabajo de Riesgo</field></record>
        <record id="e01_28" model="einvoice.catalog.01"><field name="code">28</field><field name="name">Tarifa Unificada de Uso de Aeropuerto</field></record>
        <record id="e01_29" model="einvoice.catalog.01"><field name="code">29</field><field name="name">Documentos emitidos por la COFOPRI en calidad de oferta de venta de terrenos, los correspondientes a las subastas públicas y a la retribución de los servicios que presta</field></record>
        <record id="e01_30" model="einvoice.catalog.01"><field name="code">30</field><field name="name">Documentos emitidos por las empresas que desempeñan el rol adquirente en los sistemas de pago mediante tarjetas de crédito y débito</field></record>
        <record id="e01_31" model="einvoice.catalog.01"><field name="code">31</field><field name="name">Guía de Remisión - Transportista</field></record>
        <record id="e01_32" model="einvoice.catalog.01"><field name="code">32</field><field name="name">Documentos emitidos por las empresas recaudadoras de la denominada Garantía de Red Principal a la que hace referencia el numeral 7.6 del artículo 7° de la Ley N° 27133 – Ley de Promoción del Desarrollo de la Industria del Gas Natural </field></record>
        <record id="e01_34" model="einvoice.catalog.01"><field name="code">34</field><field name="name">Documento del Operador</field></record>
        <record id="e01_35" model="einvoice.catalog.01"><field name="code">35</field><field name="name">Documento del Partícipe</field></record>
        <record id="e01_36" model="einvoice.catalog.01"><field name="code">36</field><field name="name">Recibo de Distribución de Gas Natural</field></record>
        <record id="e01_37" model="einvoice.catalog.01"><field name="code">37</field><field name="name">Documentos que emitan los concesionarios del servicio de revisiones técnicas vehiculares, por la prestación de dicho servicio </field></record>
        <record id="e01_40" model="einvoice.catalog.01"><field name="code">40</field><field name="name">Constancia de Depósito - IVAP (Ley 28211)</field></record>
        <record id="e01_50" model="einvoice.catalog.01"><field name="code">50</field><field name="name">Declaración Única de Aduanas - Importación definitiva</field></record>
        <record id="e01_52" model="einvoice.catalog.01"><field name="code">52</field><field name="name">Despacho Simplificado - Importación Simplificada</field></record>
        <record id="e01_53" model="einvoice.catalog.01"><field name="code">53</field><field name="name">Declaración de Mensajería o Courier</field></record>
        <record id="e01_54" model="einvoice.catalog.01"><field name="code">54</field><field name="name">Liquidación de Cobranza</field></record>
        <record id="e01_87" model="einvoice.catalog.01"><field name="code">87</field><field name="name">Nota de Crédito Especial</field></record>
        <record id="e01_88" model="einvoice.catalog.01"><field name="code">88</field><field name="name">Nota de Débito Especial</field></record>
        <record id="e01_91" model="einvoice.catalog.01"><field name="code">91</field><field name="name">Comprobante de No Domiciliado</field></record>
        <record id="e01_96" model="einvoice.catalog.01"><field name="code">96</field><field name="name">Exceso de crédito fiscal por retiro de bienes</field></record>
        <record id="e01_97" model="einvoice.catalog.01"><field name="code">97</field><field name="name">Nota de Crédito - No Domiciliado</field></record>
        <record id="e01_98" model="einvoice.catalog.01"><field name="code">98</field><field name="name">Nota de Débito - No Domiciliado</field></record>
        <record id="e01_99" model="einvoice.catalog.01"><field name="code">99</field><field name="name">Otros -  Consolidado de Boletas de Venta</field></record>
        
        <!-- Catalogo 06 - Tipos de documento de Identitdad -->
        <record id="e06_0" model="einvoice.catalog.06"><field name="code">0</field><field name="name">DOC.TRIB.NO.DOM.SIN.RUC</field><field name="default">-</field></record>
        <record id="e06_1" model="einvoice.catalog.06"><field name="code">1</field><field name="name">DNI</field><field name="default">00000000</field></record>
        <record id="e06_4" model="einvoice.catalog.06"><field name="code">4</field><field name="name">Carnet de Extrangería</field></record>
        <record id="e06_6" model="einvoice.catalog.06"><field name="code">6</field><field name="name">RUC</field></record>
        <record id="e06_7" model="einvoice.catalog.06"><field name="code">7</field><field name="name">Pasaporte</field></record>
        <record id="e06_A" model="einvoice.catalog.06"><field name="code">A</field><field name="name">Cédula Diplomática de Identidad</field></record>
        
        <!-- Catalogo 07  - Códigos de Tipo de Afectación del IGV  -->
        <record id="e07_10" model="einvoice.catalog.07"><field name="code">10</field><field name="name">Gravado - Operación Onerosa</field><field name="no_onerosa" eval="False"/><field name="type">gravado</field></record>
        <record id="e07_11" model="einvoice.catalog.07"><field name="code">11</field><field name="name">Gravado – Retiro por premio</field><field name="no_onerosa" eval="True"/><field name="type">gravado</field></record>
        <record id="e07_12" model="einvoice.catalog.07"><field name="code">12</field><field name="name">Gravado – Retiro por donación</field><field name="no_onerosa" eval="True"/><field name="type">gravado</field></record>
        <record id="e07_13" model="einvoice.catalog.07"><field name="code">13</field><field name="name">Gravado – Retiro</field><field name="no_onerosa" eval="True"/><field name="type">gravado</field></record>
        <record id="e07_14" model="einvoice.catalog.07"><field name="code">14</field><field name="name">Gravado – Retiro por publicidad</field><field name="no_onerosa" eval="True"/><field name="type">gravado</field></record>
        <record id="e07_15" model="einvoice.catalog.07"><field name="code">15</field><field name="name">Gravado – Bonificaciones</field><field name="no_onerosa" eval="True"/><field name="type">gravado</field></record>
        <record id="e07_16" model="einvoice.catalog.07"><field name="code">16</field><field name="name">Gravado – Retiro por entrega a trabajadores</field><field name="no_onerosa" eval="True"/><field name="type">gravado</field></record>
        <record id="e07_20" model="einvoice.catalog.07"><field name="code">20</field><field name="name">Exonerado - Operación Onerosa</field><field name="no_onerosa" eval="False"/><field name="type">exonerado</field></record>
        <record id="e07_30" model="einvoice.catalog.07"><field name="code">30</field><field name="name">Inafecto - Operación Onerosa</field><field name="no_onerosa" eval="False"/><field name="type">inafecto</field></record>
        <record id="e07_31" model="einvoice.catalog.07"><field name="code">31</field><field name="name">Inafecto – Retiro por Bonificación</field><field name="no_onerosa" eval="True"/><field name="type">inafecto</field></record>
        <record id="e07_32" model="einvoice.catalog.07"><field name="code">32</field><field name="name">Inafecto – Retiro</field><field name="no_onerosa" eval="True"/><field name="type">inafecto</field></record>
        <record id="e07_33" model="einvoice.catalog.07"><field name="code">33</field><field name="name">Inafecto – Retiro por Muestras Médicas</field><field name="no_onerosa" eval="True"/><field name="type">inafecto</field></record>
        <record id="e07_34" model="einvoice.catalog.07"><field name="code">34</field><field name="name">Inafecto - Retiro por Convenio Colectivo</field><field name="no_onerosa" eval="True"/><field name="type">inafecto</field></record>
        <record id="e07_35" model="einvoice.catalog.07"><field name="code">35</field><field name="name">Inafecto – Retiro por premio</field><field name="no_onerosa" eval="True"/><field name="type">inafecto</field></record>
        <record id="e07_36" model="einvoice.catalog.07"><field name="code">36</field><field name="name">Inafecto - Retiro por publicidad</field><field name="no_onerosa" eval="True"/><field name="type">inafecto</field></record>
        <record id="e07_40" model="einvoice.catalog.07"><field name="code">40</field><field name="name">Exportación</field><field name="no_onerosa" eval="True"/><field name="type">exonerado</field></record>
        
        <!-- Catalogo 08  - Códigos de Tipos de Sistema de Cálculo del ISC  -->
        <record id="e08_01" model="einvoice.catalog.08"><field name="code">01</field><field name="name">Sistema al valor (Apéndice IV, lit. A – T.U.O IGV e ISC)</field></record>
        <record id="e08_02" model="einvoice.catalog.08"><field name="code">02</field><field name="name">Aplicación del Monto Fijo (Apéndice IV, lit. B – T.U.O IGV e ISC)</field></record>
        <record id="e08_03" model="einvoice.catalog.08"><field name="code">03</field><field name="name">Sistema de Precios de Venta al Público (Apéndice IV, lit. C – T.U.O IGV e ISC)</field></record>
        
        <!-- Catalogo 09  - Codigos de Tipo de Nota de Credito Electronica  -->
        <record id="e09_01" model="einvoice.catalog.09"><field name="code">01</field><field name="name">Anulación de la operación</field></record>
        <record id="e09_02" model="einvoice.catalog.09"><field name="code">02</field><field name="name">Anulación por error en el RUC</field></record>
        <record id="e09_03" model="einvoice.catalog.09"><field name="code">03</field><field name="name">Corrección por error en la descripción</field></record>
        <record id="e09_04" model="einvoice.catalog.09"><field name="code">04</field><field name="name">Descuento global</field></record>
        <record id="e09_05" model="einvoice.catalog.09"><field name="code">05</field><field name="name">Descuento por ítem</field></record>
        <record id="e09_06" model="einvoice.catalog.09"><field name="code">06</field><field name="name">Devolución total</field></record>
        <record id="e09_07" model="einvoice.catalog.09"><field name="code">07</field><field name="name">Devolución por ítem</field></record>
        <record id="e09_08" model="einvoice.catalog.09"><field name="code">08</field><field name="name">Bonificación</field></record>
        <record id="e09_09" model="einvoice.catalog.09"><field name="code">09</field><field name="name">Disminución en el valor</field></record>
        
        <!-- Catalogo 10  - Codigos de Tipo de Nota de Debito Electronica  -->
        <record id="e10_01" model="einvoice.catalog.10"><field name="code">01</field><field name="name">Intereses por mora</field></record>
        <record id="e10_02" model="einvoice.catalog.10"><field name="code">02</field><field name="name">Aumento en el valor</field></record>
        
        <!-- Catalogo 16  - Códigos – Tipo de Precio de Venta Unitario  -->
        <record id="e16_01" model="einvoice.catalog.16"><field name="code">01</field><field name="name">Precio unitario (incluye el IGV)</field></record>
        <record id="e16_02" model="einvoice.catalog.16"><field name="code">02</field><field name="name">Valor referencial unitario en operaciones no onerosas</field></record>

        <!-- Catalogo 18  - Códigos – Modalidad de Traslado  -->
        <record id="e18_01" model="einvoice.catalog.18"><field name="code">01</field><field name="name">Transporte público</field></record>
        <record id="e18_02" model="einvoice.catalog.18"><field name="code">02</field><field name="name">Transporte privado</field></record>

        <!-- Catalogo 20  - Códigos – Motivos de Traslado  -->
        <record id="e20_01" model="einvoice.catalog.20"><field name="code">01</field><field name="name">VENTA</field></record>
        <record id="e20_14" model="einvoice.catalog.20"><field name="code">14</field><field name="name">VENTA SUJETA A CONFIRMACION DEL COMPRADOR</field></record>
        <record id="e20_02" model="einvoice.catalog.20"><field name="code">02</field><field name="name">COMPRA</field></record>
        <record id="e20_04" model="einvoice.catalog.20"><field name="code">04</field><field name="name">TRASLADO ENTRE ESTABLECIMIENTOS DE LA MISMA EMPRESA</field></record>
        <record id="e20_18" model="einvoice.catalog.20"><field name="code">18</field><field name="name">TRASLADO EMISOR ITINERANTE CP</field></record>
        <record id="e20_08" model="einvoice.catalog.20"><field name="code">08</field><field name="name">IMPORTACION</field></record>
        <record id="e20_09" model="einvoice.catalog.20"><field name="code">09</field><field name="name">EXPORTACION</field></record>
        <record id="e20_19" model="einvoice.catalog.20"><field name="code">19</field><field name="name">TRASLADO A ZONA PRIMARIA</field></record>
        <record id="e20_13" model="einvoice.catalog.20"><field name="code">13</field><field name="name">OTROS</field></record>

        <!-- Catalogo 13  - Códigos – UBIGEO-->
        <record id="e13_0101" model="einvoice.catalog.13"><field name="code">0101</field><field name="name">CHACHAPOYAS</field></record>
        <record id="e13_0102" model="einvoice.catalog.13"><field name="code">0102</field><field name="name">BAGUA</field></record>
        <record id="e13_0103" model="einvoice.catalog.13"><field name="code">0103</field><field name="name">JUMBILLA</field></record>
        <record id="e13_0104" model="einvoice.catalog.13"><field name="code">0104</field><field name="name">SANTA MARIA DE NIEVA</field></record>
        <record id="e13_0105" model="einvoice.catalog.13"><field name="code">0105</field><field name="name">LAMUD</field></record>
        <record id="e13_0106" model="einvoice.catalog.13"><field name="code">0106</field><field name="name">MENDOZA</field></record>
        <record id="e13_0107" model="einvoice.catalog.13"><field name="code">0107</field><field name="name">BAGUA GRANDE</field></record>
        <record id="e13_0201" model="einvoice.catalog.13"><field name="code">0201</field><field name="name">HUARAZ</field></record>
        <record id="e13_0202" model="einvoice.catalog.13"><field name="code">0202</field><field name="name">AIJA</field></record>
        <record id="e13_0203" model="einvoice.catalog.13"><field name="code">0203</field><field name="name">LLAMELLIN</field></record>
        <record id="e13_0204" model="einvoice.catalog.13"><field name="code">0204</field><field name="name">CHACAS</field></record>
        <record id="e13_0205" model="einvoice.catalog.13"><field name="code">0205</field><field name="name">CHIQUIAN</field></record>
        <record id="e13_0206" model="einvoice.catalog.13"><field name="code">0206</field><field name="name">CARHUAZ</field></record>
        <record id="e13_0207" model="einvoice.catalog.13"><field name="code">0207</field><field name="name">SAN LUIS</field></record>
        <record id="e13_0208" model="einvoice.catalog.13"><field name="code">0208</field><field name="name">CASMA</field></record>
        <record id="e13_0209" model="einvoice.catalog.13"><field name="code">0209</field><field name="name">CORONGO</field></record>
        <record id="e13_0210" model="einvoice.catalog.13"><field name="code">0210</field><field name="name">HUARI</field></record>
        <record id="e13_0211" model="einvoice.catalog.13"><field name="code">0211</field><field name="name">HUARMEY</field></record>
        <record id="e13_0212" model="einvoice.catalog.13"><field name="code">0212</field><field name="name">CARAZ</field></record>
        <record id="e13_0213" model="einvoice.catalog.13"><field name="code">0213</field><field name="name">PISCOBAMBA</field></record>
        <record id="e13_0214" model="einvoice.catalog.13"><field name="code">0214</field><field name="name">OCROS</field></record>
        <record id="e13_0215" model="einvoice.catalog.13"><field name="code">0215</field><field name="name">CABANA</field></record>
        <record id="e13_0216" model="einvoice.catalog.13"><field name="code">0216</field><field name="name">POMABAMBA</field></record>
        <record id="e13_0217" model="einvoice.catalog.13"><field name="code">0217</field><field name="name">RECUAY</field></record>
        <record id="e13_0218" model="einvoice.catalog.13"><field name="code">0218</field><field name="name">CHIMBOTE</field></record>
        <record id="e13_0219" model="einvoice.catalog.13"><field name="code">0219</field><field name="name">SIHUAS</field></record>
        <record id="e13_0220" model="einvoice.catalog.13"><field name="code">0220</field><field name="name">YUNGAY</field></record>
        <record id="e13_0301" model="einvoice.catalog.13"><field name="code">0301</field><field name="name">ABANCAY</field></record>
        <record id="e13_0302" model="einvoice.catalog.13"><field name="code">0302</field><field name="name">ANDAHUAYLAS</field></record>
        <record id="e13_0303" model="einvoice.catalog.13"><field name="code">0303</field><field name="name">ANTABAMBA</field></record>
        <record id="e13_0304" model="einvoice.catalog.13"><field name="code">0304</field><field name="name">CHALHUANCA</field></record>
        <record id="e13_0305" model="einvoice.catalog.13"><field name="code">0305</field><field name="name">TAMBOBAMBA</field></record>
        <record id="e13_0306" model="einvoice.catalog.13"><field name="code">0306</field><field name="name">CHINCHEROS</field></record>
        <record id="e13_0307" model="einvoice.catalog.13"><field name="code">0307</field><field name="name">CHUQUIBAMBILLA</field></record>
        <record id="e13_0401" model="einvoice.catalog.13"><field name="code">0401</field><field name="name">AREQUIPA</field></record>
        <record id="e13_0402" model="einvoice.catalog.13"><field name="code">0402</field><field name="name">CAMANA</field></record>
        <record id="e13_0403" model="einvoice.catalog.13"><field name="code">0403</field><field name="name">CARAVELI</field></record>
        <record id="e13_0404" model="einvoice.catalog.13"><field name="code">0404</field><field name="name">APLAO</field></record>
        <record id="e13_0405" model="einvoice.catalog.13"><field name="code">0405</field><field name="name">CHIVAY</field></record>
        <record id="e13_0406" model="einvoice.catalog.13"><field name="code">0406</field><field name="name">CHUQUIBAMBA</field></record>
        <record id="e13_0407" model="einvoice.catalog.13"><field name="code">0407</field><field name="name">MOLLENDO</field></record>
        <record id="e13_0408" model="einvoice.catalog.13"><field name="code">0408</field><field name="name">COTAHUASI</field></record>
        <record id="e13_0501" model="einvoice.catalog.13"><field name="code">0501</field><field name="name">AYACUCHO</field></record>
        <record id="e13_0502" model="einvoice.catalog.13"><field name="code">0502</field><field name="name">CANGALLO</field></record>
        <record id="e13_0503" model="einvoice.catalog.13"><field name="code">0503</field><field name="name">HUANCA SANCOS</field></record>
        <record id="e13_0504" model="einvoice.catalog.13"><field name="code">0504</field><field name="name">HUANTA</field></record>
        <record id="e13_0505" model="einvoice.catalog.13"><field name="code">0505</field><field name="name">SAN MIGUEL</field></record>
        <record id="e13_0506" model="einvoice.catalog.13"><field name="code">0506</field><field name="name">PUQUIO</field></record>
        <record id="e13_0507" model="einvoice.catalog.13"><field name="code">0507</field><field name="name">CORACORA</field></record>
        <record id="e13_0508" model="einvoice.catalog.13"><field name="code">0508</field><field name="name">PAUSA</field></record>
        <record id="e13_0509" model="einvoice.catalog.13"><field name="code">0509</field><field name="name">QUEROBAMBA</field></record>
        <record id="e13_0510" model="einvoice.catalog.13"><field name="code">0510</field><field name="name">HUANCAPI</field></record>
        <record id="e13_0511" model="einvoice.catalog.13"><field name="code">0511</field><field name="name">VILCAS HUAMAN</field></record>
        <record id="e13_0601" model="einvoice.catalog.13"><field name="code">0601</field><field name="name">CAJAMARCA</field></record>
        <record id="e13_0602" model="einvoice.catalog.13"><field name="code">0602</field><field name="name">CAJABAMBA</field></record>
        <record id="e13_0603" model="einvoice.catalog.13"><field name="code">0603</field><field name="name">CELENDIN</field></record>
        <record id="e13_0604" model="einvoice.catalog.13"><field name="code">0604</field><field name="name">CHOTA</field></record>
        <record id="e13_0605" model="einvoice.catalog.13"><field name="code">0605</field><field name="name">CONTUMAZA</field></record>
        <record id="e13_0606" model="einvoice.catalog.13"><field name="code">0606</field><field name="name">CUTERVO</field></record>
        <record id="e13_0607" model="einvoice.catalog.13"><field name="code">0607</field><field name="name">BAMBAMARCA</field></record>
        <record id="e13_0608" model="einvoice.catalog.13"><field name="code">0608</field><field name="name">JAEN</field></record>
        <record id="e13_0609" model="einvoice.catalog.13"><field name="code">0609</field><field name="name">SAN IGNACIO</field></record>
        <record id="e13_0610" model="einvoice.catalog.13"><field name="code">0610</field><field name="name">SAN MARCOS</field></record>
        <record id="e13_0611" model="einvoice.catalog.13"><field name="code">0611</field><field name="name">SAN MIGUEL DE PALLAQUES</field></record>
        <record id="e13_0612" model="einvoice.catalog.13"><field name="code">0612</field><field name="name">SAN PABLO</field></record>
        <record id="e13_0613" model="einvoice.catalog.13"><field name="code">0613</field><field name="name">SANTA CRUZ DE SUCCHABAMBA</field></record>
        <record id="e13_0701" model="einvoice.catalog.13"><field name="code">0701</field><field name="name">CALLAO</field></record>
        <record id="e13_0801" model="einvoice.catalog.13"><field name="code">0801</field><field name="name">CUSCO</field></record>
        <record id="e13_0802" model="einvoice.catalog.13"><field name="code">0802</field><field name="name">ACOMAYO</field></record>
        <record id="e13_0803" model="einvoice.catalog.13"><field name="code">0803</field><field name="name">ANTA</field></record>
        <record id="e13_0804" model="einvoice.catalog.13"><field name="code">0804</field><field name="name">CALCA</field></record>
        <record id="e13_0805" model="einvoice.catalog.13"><field name="code">0805</field><field name="name">YANAOCA</field></record>
        <record id="e13_0806" model="einvoice.catalog.13"><field name="code">0806</field><field name="name">SICUANI</field></record>
        <record id="e13_0807" model="einvoice.catalog.13"><field name="code">0807</field><field name="name">SANTO TOMAS</field></record>
        <record id="e13_0808" model="einvoice.catalog.13"><field name="code">0808</field><field name="name">ESPINAR</field></record>
        <record id="e13_0809" model="einvoice.catalog.13"><field name="code">0809</field><field name="name">QUILLABAMBA</field></record>
        <record id="e13_0810" model="einvoice.catalog.13"><field name="code">0810</field><field name="name">PARURO</field></record>
        <record id="e13_0811" model="einvoice.catalog.13"><field name="code">0811</field><field name="name">PAUCARTAMBO</field></record>
        <record id="e13_0812" model="einvoice.catalog.13"><field name="code">0812</field><field name="name">URCOS</field></record>
        <record id="e13_0813" model="einvoice.catalog.13"><field name="code">0813</field><field name="name">URUBAMBA</field></record>
        <record id="e13_0901" model="einvoice.catalog.13"><field name="code">0901</field><field name="name">HUANCAVELICA</field></record>
        <record id="e13_0902" model="einvoice.catalog.13"><field name="code">0902</field><field name="name">ACOBAMBA</field></record>
        <record id="e13_0903" model="einvoice.catalog.13"><field name="code">0903</field><field name="name">LIRCAY</field></record>
        <record id="e13_0904" model="einvoice.catalog.13"><field name="code">0904</field><field name="name">CASTROVIRREYNA</field></record>
        <record id="e13_0905" model="einvoice.catalog.13"><field name="code">0905</field><field name="name">CHURCAMPA</field></record>
        <record id="e13_0906" model="einvoice.catalog.13"><field name="code">0906</field><field name="name">HUAYTARA</field></record>
        <record id="e13_0907" model="einvoice.catalog.13"><field name="code">0907</field><field name="name">PAMPAS</field></record>
        <record id="e13_1001" model="einvoice.catalog.13"><field name="code">1001</field><field name="name">HUANUCO</field></record>
        <record id="e13_1002" model="einvoice.catalog.13"><field name="code">1002</field><field name="name">AMBO</field></record>
        <record id="e13_1003" model="einvoice.catalog.13"><field name="code">1003</field><field name="name">LA UNION</field></record>
        <record id="e13_1004" model="einvoice.catalog.13"><field name="code">1004</field><field name="name">HUACAYBAMBA</field></record>
        <record id="e13_1005" model="einvoice.catalog.13"><field name="code">1005</field><field name="name">LLATA</field></record>
        <record id="e13_1006" model="einvoice.catalog.13"><field name="code">1006</field><field name="name">TINGO MARIA</field></record>
        <record id="e13_1007" model="einvoice.catalog.13"><field name="code">1007</field><field name="name">HUACRACHUCO</field></record>
        <record id="e13_1008" model="einvoice.catalog.13"><field name="code">1008</field><field name="name">PANAO</field></record>
        <record id="e13_1009" model="einvoice.catalog.13"><field name="code">1009</field><field name="name">PUERTO INCA</field></record>
        <record id="e13_1010" model="einvoice.catalog.13"><field name="code">1010</field><field name="name">JESUS</field></record>
        <record id="e13_1011" model="einvoice.catalog.13"><field name="code">1011</field><field name="name">CHAVINILLO</field></record>
        <record id="e13_1101" model="einvoice.catalog.13"><field name="code">1101</field><field name="name">ICA</field></record>
        <record id="e13_1102" model="einvoice.catalog.13"><field name="code">1101</field><field name="name">CHINCHA ALTA</field></record>
        <record id="e13_1103" model="einvoice.catalog.13"><field name="code">1101</field><field name="name">NASCA</field></record>
        <record id="e13_1104" model="einvoice.catalog.13"><field name="code">1101</field><field name="name">PALPA</field></record>
        <record id="e13_1105" model="einvoice.catalog.13"><field name="code">1101</field><field name="name">PISCO</field></record>
        <record id="e13_1201" model="einvoice.catalog.13"><field name="code">1201</field><field name="name">HUANCAYO</field></record>
        <record id="e13_1202" model="einvoice.catalog.13"><field name="code">1202</field><field name="name">CONCEPCION</field></record>
        <record id="e13_1203" model="einvoice.catalog.13"><field name="code">1203</field><field name="name">LA MERCED</field></record>
        <record id="e13_1204" model="einvoice.catalog.13"><field name="code">1204</field><field name="name">JAUJA</field></record>
        <record id="e13_1205" model="einvoice.catalog.13"><field name="code">1205</field><field name="name">JUNIN</field></record>
        <record id="e13_1206" model="einvoice.catalog.13"><field name="code">1206</field><field name="name">SATIPO</field></record>
        <record id="e13_1207" model="einvoice.catalog.13"><field name="code">1207</field><field name="name">TARMA</field></record>
        <record id="e13_1208" model="einvoice.catalog.13"><field name="code">1208</field><field name="name">LA OROYA</field></record>
        <record id="e13_1209" model="einvoice.catalog.13"><field name="code">1209</field><field name="name">CHUPACA</field></record>
        <record id="e13_1301" model="einvoice.catalog.13"><field name="code">1301</field><field name="name">TRUJILLO</field></record>
        <record id="e13_1302" model="einvoice.catalog.13"><field name="code">1302</field><field name="name">ASCOPE</field></record>
        <record id="e13_1303" model="einvoice.catalog.13"><field name="code">1303</field><field name="name">BOLIVAR</field></record>
        <record id="e13_1304" model="einvoice.catalog.13"><field name="code">1304</field><field name="name">CHEPEN</field></record>
        <record id="e13_1305" model="einvoice.catalog.13"><field name="code">1305</field><field name="name">JULCAN</field></record>
        <record id="e13_1306" model="einvoice.catalog.13"><field name="code">1306</field><field name="name">OTUZCO</field></record>
        <record id="e13_1307" model="einvoice.catalog.13"><field name="code">1307</field><field name="name">SAN PEDRO DE LLOC</field></record>
        <record id="e13_1308" model="einvoice.catalog.13"><field name="code">1308</field><field name="name">TAYABAMBA</field></record>
        <record id="e13_1309" model="einvoice.catalog.13"><field name="code">1309</field><field name="name">HUAMACHUCO</field></record>
        <record id="e13_1310" model="einvoice.catalog.13"><field name="code">1310</field><field name="name">SANTIAGO DE CHUCO</field></record>
        <record id="e13_1311" model="einvoice.catalog.13"><field name="code">1311</field><field name="name">CASCAS</field></record>
        <record id="e13_1312" model="einvoice.catalog.13"><field name="code">1312</field><field name="name">VIRU</field></record>
        <record id="e13_1401" model="einvoice.catalog.13"><field name="code">1401</field><field name="name">CHICLAYO</field></record>
        <record id="e13_1402" model="einvoice.catalog.13"><field name="code">1402</field><field name="name">FERREÑAFE</field></record>
        <record id="e13_1403" model="einvoice.catalog.13"><field name="code">1403</field><field name="name">LAMBAYEQUE</field></record>
        <record id="e13_1501" model="einvoice.catalog.13"><field name="code">1501</field><field name="name">LIMA</field></record>
        <record id="e13_1502" model="einvoice.catalog.13"><field name="code">1502</field><field name="name">BARRANCA</field></record>
        <record id="e13_1503" model="einvoice.catalog.13"><field name="code">1503</field><field name="name">CAJATAMBO</field></record>
        <record id="e13_1504" model="einvoice.catalog.13"><field name="code">1504</field><field name="name">CANTA</field></record>
        <record id="e13_1505" model="einvoice.catalog.13"><field name="code">1505</field><field name="name">SAN VICENTE DE CAÑETE</field></record>
        <record id="e13_1506" model="einvoice.catalog.13"><field name="code">1506</field><field name="name">HUARAL</field></record>
        <record id="e13_1507" model="einvoice.catalog.13"><field name="code">1507</field><field name="name">MATUCANA</field></record>
        <record id="e13_1508" model="einvoice.catalog.13"><field name="code">1508</field><field name="name">HUACHO</field></record>
        <record id="e13_1509" model="einvoice.catalog.13"><field name="code">1509</field><field name="name">OYON</field></record>
        <record id="e13_1510" model="einvoice.catalog.13"><field name="code">1510</field><field name="name">YAUYOS</field></record>
        <record id="e13_1601" model="einvoice.catalog.13"><field name="code">1601</field><field name="name">IQUITOS</field></record>
        <record id="e13_1602" model="einvoice.catalog.13"><field name="code">1602</field><field name="name">YURIMAGUAS</field></record>
        <record id="e13_1603" model="einvoice.catalog.13"><field name="code">1603</field><field name="name">NAUTA</field></record>
        <record id="e13_1604" model="einvoice.catalog.13"><field name="code">1604</field><field name="name">CABALLOCOCHA</field></record>
        <record id="e13_1605" model="einvoice.catalog.13"><field name="code">1605</field><field name="name">REQUENA</field></record>
        <record id="e13_1606" model="einvoice.catalog.13"><field name="code">1606</field><field name="name">CONTAMANA</field></record>
        <record id="e13_1607" model="einvoice.catalog.13"><field name="code">1607</field><field name="name">SAN LORENZO</field></record>
        <record id="e13_1608" model="einvoice.catalog.13"><field name="code">1608</field><field name="name">SAN ANTONIO DEL ESTRECHO</field></record>
        <record id="e13_1701" model="einvoice.catalog.13"><field name="code">1701</field><field name="name">PUERTO MALDONADO</field></record>
        <record id="e13_1702" model="einvoice.catalog.13"><field name="code">1702</field><field name="name">MANU</field></record>
        <record id="e13_1703" model="einvoice.catalog.13"><field name="code">1703</field><field name="name">IÑAPARI</field></record>
        <record id="e13_1801" model="einvoice.catalog.13"><field name="code">1801</field><field name="name">MOQUEGUA</field></record>
        <record id="e13_1802" model="einvoice.catalog.13"><field name="code">1802</field><field name="name">OMATE</field></record>
        <record id="e13_1803" model="einvoice.catalog.13"><field name="code">1803</field><field name="name">ILO</field></record>
        <record id="e13_1901" model="einvoice.catalog.13"><field name="code">1901</field><field name="name">CERRO DE PASCO</field></record>
        <record id="e13_1902" model="einvoice.catalog.13"><field name="code">1902</field><field name="name">YANAHUANCA</field></record>
        <record id="e13_1903" model="einvoice.catalog.13"><field name="code">1903</field><field name="name">OXAPAMPA</field></record>
        <record id="e13_2001" model="einvoice.catalog.13"><field name="code">2001</field><field name="name">PIURA</field></record>
        <record id="e13_2002" model="einvoice.catalog.13"><field name="code">2002</field><field name="name">AYABACA</field></record>
        <record id="e13_2003" model="einvoice.catalog.13"><field name="code">2003</field><field name="name">HUANCABAMBA</field></record>
        <record id="e13_2004" model="einvoice.catalog.13"><field name="code">2004</field><field name="name">CHULUCANAS</field></record>
        <record id="e13_2005" model="einvoice.catalog.13"><field name="code">2005</field><field name="name">PAITA</field></record>
        <record id="e13_2006" model="einvoice.catalog.13"><field name="code">2006</field><field name="name">SULLANA</field></record>
        <record id="e13_2007" model="einvoice.catalog.13"><field name="code">2007</field><field name="name">TALARA</field></record>
        <record id="e13_2008" model="einvoice.catalog.13"><field name="code">2008</field><field name="name">SECHURA</field></record>
        <record id="e13_2101" model="einvoice.catalog.13"><field name="code">2101</field><field name="name">PUNO</field></record>
        <record id="e13_2102" model="einvoice.catalog.13"><field name="code">2102</field><field name="name">AZANGARO</field></record>
        <record id="e13_2103" model="einvoice.catalog.13"><field name="code">2103</field><field name="name">MACUSANI</field></record>
        <record id="e13_2104" model="einvoice.catalog.13"><field name="code">2104</field><field name="name">JULI</field></record>
        <record id="e13_2105" model="einvoice.catalog.13"><field name="code">2105</field><field name="name">ILAVE</field></record>
        <record id="e13_2106" model="einvoice.catalog.13"><field name="code">2106</field><field name="name">HUANCANE</field></record>
        <record id="e13_2107" model="einvoice.catalog.13"><field name="code">2107</field><field name="name">LAMPA</field></record>
        <record id="e13_2108" model="einvoice.catalog.13"><field name="code">2108</field><field name="name">AYAVIRI</field></record>
        <record id="e13_2109" model="einvoice.catalog.13"><field name="code">2109</field><field name="name">MOHO</field></record>
        <record id="e13_2110" model="einvoice.catalog.13"><field name="code">2110</field><field name="name">PUTINA</field></record>
        <record id="e13_2111" model="einvoice.catalog.13"><field name="code">2111</field><field name="name">JULIACA</field></record>
        <record id="e13_2112" model="einvoice.catalog.13"><field name="code">2112</field><field name="name">SANDIA</field></record>
        <record id="e13_2113" model="einvoice.catalog.13"><field name="code">2113</field><field name="name">YUNGUYO</field></record>
        <record id="e13_2201" model="einvoice.catalog.13"><field name="code">2201</field><field name="name">MOYOBAMBA</field></record>
        <record id="e13_2202" model="einvoice.catalog.13"><field name="code">2202</field><field name="name">BELLAVISTA</field></record>
        <record id="e13_2203" model="einvoice.catalog.13"><field name="code">2203</field><field name="name">SAN JOSE DE SISA</field></record>
        <record id="e13_2204" model="einvoice.catalog.13"><field name="code">2204</field><field name="name">SAPOSOA</field></record>
        <record id="e13_2205" model="einvoice.catalog.13"><field name="code">2205</field><field name="name">LAMAS</field></record>
        <record id="e13_2206" model="einvoice.catalog.13"><field name="code">2206</field><field name="name">JUANJUI</field></record>
        <record id="e13_2207" model="einvoice.catalog.13"><field name="code">2207</field><field name="name">PICOTA</field></record>
        <record id="e13_2208" model="einvoice.catalog.13"><field name="code">2208</field><field name="name">RIOJA</field></record>
        <record id="e13_2209" model="einvoice.catalog.13"><field name="code">2209</field><field name="name">TARAPOTO</field></record>
        <record id="e13_2210" model="einvoice.catalog.13"><field name="code">2210</field><field name="name">TOCACHE</field></record>
        <record id="e13_2301" model="einvoice.catalog.13"><field name="code">2301</field><field name="name">TACNA</field></record>
        <record id="e13_2302" model="einvoice.catalog.13"><field name="code">2302</field><field name="name">CANDARAVE</field></record>
        <record id="e13_2303" model="einvoice.catalog.13"><field name="code">2303</field><field name="name">LOCUMBA</field></record>
        <record id="e13_2304" model="einvoice.catalog.13"><field name="code">2304</field><field name="name">TARATA</field></record>
        <record id="e13_2401" model="einvoice.catalog.13"><field name="code">2401</field><field name="name">TUMBES</field></record>
        <record id="e13_2402" model="einvoice.catalog.13"><field name="code">2402</field><field name="name">ZORRITOS</field></record>
        <record id="e13_2403" model="einvoice.catalog.13"><field name="code">2403</field><field name="name">ZARUMILLA</field></record>
        <record id="e13_2501" model="einvoice.catalog.13"><field name="code">2501</field><field name="name">PUCALLPA</field></record>
        <record id="e13_2502" model="einvoice.catalog.13"><field name="code">2502</field><field name="name">ATALAYA</field></record>
        <record id="e13_2503" model="einvoice.catalog.13"><field name="code">2503</field><field name="name">AGUAYTIA</field></record>
        <record id="e13_2504" model="einvoice.catalog.13"><field name="code">2504</field><field name="name">ESPERANZA</field></record>
        
    </data>
</openerp>
